hdlcomposer/__init__.py
hdlcomposer/signals/__init__.py
hdlcomposer/signals/signals.py
hdlcomposer/sim/__init__.py
hdlcomposer/sim/ghdl/__init__.py
hdlcomposer/sim/ghdl/ghdl.py
hdlcomposer/sim/ghdl/parse.py
hdlcomposer/utils/__init__.py
hdlcomposer/utils/general.py
hdlcomposer/vcd/__init__.py
hdlcomposer/vcd/parse.py
hdlcomposer/vcd/utils.py
hdlcomposer/verilog/__init__.py
hdlcomposer/vhdl/__init__.py
hdlcomposer/vhdl/units.py
hdlcomposer/vhdl/utils.py
hdlcomposer-0.32.data/scripts/ghdl_cli
hdlcomposer-0.32.dist-info/LICENSE
hdlcomposer-0.32.dist-info/METADATA
hdlcomposer-0.32.dist-info/WHEEL
hdlcomposer-0.32.dist-info/entry_points.txt
hdlcomposer-0.32.dist-info/top_level.txt
hdlcomposer-0.32.dist-info/RECORD
