Metadata-Version: 2.1
Name: hdlcomposer
Version: 0.32
Summary: HDL simulation and autoverification made agile
Home-page: https://github.com/bmpenuelas/hdlcomposer
Author: Borja Penuelas
Author-email: bmpenuelas@gmail.com
License: MIT
Keywords: VHDL Verilog simulation verification parse hierarchy
Platform: UNKNOWN
Classifier: Development Status :: 3 - Alpha
Classifier: Programming Language :: Python :: 3
Requires-Dist: vcdvcd
